pyCreateWindow/__init__.py
pyCreateWindow-1.0.0.dist-info/LICENSE
pyCreateWindow-1.0.0.dist-info/METADATA
pyCreateWindow-1.0.0.dist-info/WHEEL
pyCreateWindow-1.0.0.dist-info/top_level.txt
pyCreateWindow-1.0.0.dist-info/RECORD
