Metadata-Version: 2.1
Name: pyCreateWindow
Version: 1.0.0
Summary: pyCreateWindow - SujithSouryaYedida
Home-page: UNKNOWN
Author: SujithSouryaYedida
Author-email: sujithsourya.yedida@gmail.com
License: UNKNOWN
Keywords: python,py,yedida,python tutorial,SujithSouryaYedida,create,window,create window,pyCreateWindow
Platform: UNKNOWN
Classifier: Development Status :: 1 - Planning
Classifier: Intended Audience :: Developers
Classifier: Programming Language :: Python :: 3
Classifier: Operating System :: Unix
Classifier: Operating System :: MacOS :: MacOS X
Classifier: Operating System :: Microsoft :: Windows
License-File: LICENSE
Requires-Dist: pyQt5
Requires-Dist: pyfiglet
Requires-Dist: colorama
Requires-Dist: pyQtWebEngine
